datalab/__init__.py
datalab/app.py
datalab/config.py
datalab/env.py
datalab/objectmodel.py
datalab/plugins.py
datalab/adapters_metadata/__init__.py
datalab/adapters_metadata/base_adapter.py
datalab/adapters_metadata/common.py
datalab/adapters_metadata/geometry_adapter.py
datalab/adapters_metadata/table_adapter.py
datalab/adapters_plotpy/__init__.py
datalab/adapters_plotpy/annotations.py
datalab/adapters_plotpy/base.py
datalab/adapters_plotpy/converters.py
datalab/adapters_plotpy/coordutils.py
datalab/adapters_plotpy/factories.py
datalab/adapters_plotpy/objects/__init__.py
datalab/adapters_plotpy/objects/base.py
datalab/adapters_plotpy/objects/image.py
datalab/adapters_plotpy/objects/scalar.py
datalab/adapters_plotpy/objects/signal.py
datalab/adapters_plotpy/roi/__init__.py
datalab/adapters_plotpy/roi/base.py
datalab/adapters_plotpy/roi/factory.py
datalab/adapters_plotpy/roi/image.py
datalab/adapters_plotpy/roi/signal.py
datalab/control/__init__.py
datalab/control/baseproxy.py
datalab/control/proxy.py
datalab/control/remote.py
datalab/data/doc/DataLab_en.pdf
datalab/data/doc/DataLab_fr.pdf
datalab/data/icons/analysis.svg
datalab/data/icons/apply.svg
datalab/data/icons/check_all.svg
datalab/data/icons/collapse.svg
datalab/data/icons/collapse_selection.svg
datalab/data/icons/console.svg
datalab/data/icons/edit.svg
datalab/data/icons/expand.svg
datalab/data/icons/expand_selection.svg
datalab/data/icons/group.svg
datalab/data/icons/help_pdf.svg
datalab/data/icons/history.svg
datalab/data/icons/image.svg
datalab/data/icons/io.svg
datalab/data/icons/libre-camera-flash-off.svg
datalab/data/icons/libre-camera-flash-on.svg
datalab/data/icons/libre-gui-about.svg
datalab/data/icons/libre-gui-action-delete.svg
datalab/data/icons/libre-gui-add.svg
datalab/data/icons/libre-gui-arrow-down.svg
datalab/data/icons/libre-gui-arrow-left.svg
datalab/data/icons/libre-gui-arrow-right.svg
datalab/data/icons/libre-gui-arrow-up.svg
datalab/data/icons/libre-gui-close.svg
datalab_platform-1.0.3.dist-info/licenses/LICENSE
datalab_platform-1.0.3.dist-info/METADATA
datalab_platform-1.0.3.dist-info/WHEEL
datalab_platform-1.0.3.dist-info/entry_points.txt
datalab_platform-1.0.3.dist-info/top_level.txt
datalab_platform-1.0.3.dist-info/RECORD
