Metadata-Version: 2.4
Name: datalab-platform
Version: 1.0.3
Summary: DataLab is a data processing and analysis software for scientific and industrial applications
Author-email: Pierre Raybaut <p.raybaut@codra.fr>
Maintainer-email: DataLab Platform Developers <p.raybaut@codra.fr>
License-Expression: BSD-3-Clause
Project-URL: Homepage, https://datalab-platform.com/
Project-URL: Documentation, https://datalab-platform.com/
Classifier: Development Status :: 5 - Production/Stable
Classifier: Intended Audience :: Developers
Classifier: Intended Audience :: Education
Classifier: Intended Audience :: Science/Research
Classifier: Intended Audience :: End Users/Desktop
Classifier: Operating System :: MacOS :: MacOS X
Classifier: Operating System :: Microsoft :: Windows :: Windows 7
Classifier: Operating System :: Microsoft :: Windows :: Windows 8
Classifier: Operating System :: Microsoft :: Windows :: Windows 10
Classifier: Operating System :: Microsoft :: Windows :: Windows 11
Classifier: Operating System :: POSIX :: Linux
Classifier: Programming Language :: Python :: 3.9
Classifier: Programming Language :: Python :: 3.10
Classifier: Programming Language :: Python :: 3.11
Classifier: Programming Language :: Python :: 3.12
Classifier: Programming Language :: Python :: 3.13
Classifier: Topic :: Scientific/Engineering
Classifier: Topic :: Scientific/Engineering :: Image Processing
Classifier: Topic :: Scientific/Engineering :: Human Machine Interfaces
Classifier: Topic :: Scientific/Engineering :: Visualization
Classifier: Topic :: Software Development :: Libraries :: Python Modules
Classifier: Topic :: Software Development :: Widget Sets
Requires-Python: <4,>=3.9
License-File: LICENSE
Requires-Dist: guidata>=3.13.4
Requires-Dist: PlotPy>=2.8.2
Requires-Dist: Sigima>=1.0.4
Requires-Dist: NumPy>=1.22
Requires-Dist: SciPy>=1.10.1
Requires-Dist: scikit-image>=0.19.2
Requires-Dist: pandas>=1.4
Requires-Dist: PyWavelets>=1.2
Requires-Dist: psutil>=5.8
Requires-Dist: packaging>=21.3
Provides-Extra: qt
Requires-Dist: PyQt5>=5.15.6; extra == "qt"
Provides-Extra: opencv
Requires-Dist: opencv-python-headless>=4.8.1.78; extra == "opencv"
Provides-Extra: exe
Requires-Dist: pyinstaller==6.16.0; extra == "exe"
Requires-Dist: opencv-python-headless>=4.8.1.78; extra == "exe"
Requires-Dist: PyQt5>=5.15.6; extra == "exe"
Provides-Extra: dev
Requires-Dist: build; extra == "dev"
Requires-Dist: babel; extra == "dev"
Requires-Dist: Coverage; extra == "dev"
Requires-Dist: pylint; extra == "dev"
Requires-Dist: ruff; extra == "dev"
Requires-Dist: pre-commit; extra == "dev"
Provides-Extra: doc
Requires-Dist: sphinx; extra == "doc"
Requires-Dist: sphinx_intl; extra == "doc"
Requires-Dist: sphinx-sitemap; extra == "doc"
Requires-Dist: myst_parser; extra == "doc"
Requires-Dist: sphinx_design; extra == "doc"
Requires-Dist: sphinx-copybutton; extra == "doc"
Requires-Dist: pydata-sphinx-theme; extra == "doc"
Provides-Extra: test
Requires-Dist: pytest; extra == "test"
Requires-Dist: pytest-xvfb; extra == "test"
Dynamic: license-file
